Workbook

Sheet Summary
A1: Tax Deduction & Mileage Summary
A2: ="Tax year "&Settings!B4
A4: Mileage deduction | B4: =SUMIFS(Mileage!$G$5:$G$504,Mileage!$H$5:$H$504,Settings!B4)
A5: Business miles | B5: =SUMIFS(Mileage!$E$5:$E$504,Mileage!$H$5:$H$504,Settings!B4)
A6: Other deductions | B6: =SUMIFS(Deductions!$F$5:$F$504,Deductions!$H$5:$H$504,Settings!B4)
A7: Home office deduction | B7: ='Home Office'!B15
A8: TOTAL deductions | B8: =B4+B6+B7
A9: Estimated tax saved | B9: =B8*Settings!B11
A10: Items missing receipts | B10: =COUNTIFS(Deductions!$G$5:$G$504,"N")
A12: By category
A13: Software & Subscriptions | B13: =SUMIFS(Deductions!$F$5:$F$504,Deductions!$C$5:$C$504,A13,Deductions!$H$5:$H$504,Settings!$B$4)
A14: Equipment & Hardware | B14: =SUMIFS(Deductions!$F$5:$F$504,Deductions!$C$5:$C$504,A14,Deductions!$H$5:$H$504,Settings!$B$4)
A15: Home Office | B15: =SUMIFS(Deductions!$F$5:$F$504,Deductions!$C$5:$C$504,A15,Deductions!$H$5:$H$504,Settings!$B$4)
A16: Internet & Phone | B16: =SUMIFS(Deductions!$F$5:$F$504,Deductions!$C$5:$C$504,A16,Deductions!$H$5:$H$504,Settings!$B$4)
A17: Marketing & Advertising | B17: =SUMIFS(Deductions!$F$5:$F$504,Deductions!$C$5:$C$504,A17,Deductions!$H$5:$H$504,Settings!$B$4)
A18: Professional Services | B18: =SUMIFS(Deductions!$F$5:$F$504,Deductions!$C$5:$C$504,A18,Deductions!$H$5:$H$504,Settings!$B$4)
A19: Education & Training | B19: =SUMIFS(Deductions!$F$5:$F$504,Deductions!$C$5:$C$504,A19,Deductions!$H$5:$H$504,Settings!$B$4)
A20: Travel | B20: =SUMIFS(Deductions!$F$5:$F$504,Deductions!$C$5:$C$504,A20,Deductions!$H$5:$H$504,Settings!$B$4)
A21: Meals (50%) | B21: =SUMIFS(Deductions!$F$5:$F$504,Deductions!$C$5:$C$504,A21,Deductions!$H$5:$H$504,Settings!$B$4)
A22: Contractors & Subcontractors | B22: =SUMIFS(Deductions!$F$5:$F$504,Deductions!$C$5:$C$504,A22,Deductions!$H$5:$H$504,Settings!$B$4)
A23: Bank & Payment Fees | B23: =SUMIFS(Deductions!$F$5:$F$504,Deductions!$C$5:$C$504,A23,Deductions!$H$5:$H$504,Settings!$B$4)
A24: Insurance | B24: =SUMIFS(Deductions!$F$5:$F$504,Deductions!$C$5:$C$504,A24,Deductions!$H$5:$H$504,Settings!$B$4)
... A26: Other | B26: =SUMIFS(Deductions!$F$5:$F$504,Deductions!$C$5:$C$504,A26,Deductions!$H$5:$H$504,Settings!$B$4)

Sheet Settings
A1: Settings
A2: Mileage rates are per IRS notices for 2026 - verify at irs.gov before filing.
A4: Tax year | B4: 2026
A5: Business mileage rate, Jan 1 - Jun 30 ($/mile) | B5: 0.725
A6: Business mileage rate, from rate-change date ($/mile) | B6: 0.76
A7: Rate-change date | B7: 46204
A8: Home office: simplified method rate ($/sq ft) | B8: 5
A9: Home office: sq ft used exclusively for business (max 300) | B9: 120
A10: Total home sq ft (for actual-expense method) | B10: 900
A11: Combined marginal tax rate (for savings estimate) | B11: 0.25
A13: Note: the mileage rate was reported raised mid-2026 (72.5c to 76c from Jul 1). If your rates differ, just edit B5:B7.

Sheet Mileage
A1: Mileage log
A2: Date, purpose and miles. Rate and deduction fill automatically.
A4: Date | B4: Purpose / client | C4: From | D4: To | E4: Miles | F4: Rate | G4: Deduction | H4: Year
A5: 46084 | B5: Acme kickoff | C5: Home | D5: Acme HQ | E5: 40 | F5: =IF(OR(A5="",E5=""),"",IF(A5>=Settings!$B$7,Settings!$B$6,Settings!$B$5)) | G5: =IF(F5="","",E5*F5) | H5: =IF(A5="","",YEAR(A5))
A6: 46193 | B6: Client visit | C6: Home | D6: Cobalt | E6: 100 | F6: =IF(OR(A6="",E6=""),"",IF(A6>=Settings!$B$7,Settings!$B$6,Settings!$B$5)) | G6: =IF(F6="","",E6*F6) | H6: =IF(A6="","",YEAR(A6))
A7: 46239 | B7: Conference | C7: Home | D7: Expo | E7: 200 | F7: =IF(OR(A7="",E7=""),"",IF(A7>=Settings!$B$7,Settings!$B$6,Settings!$B$5)) | G7: =IF(F7="","",E7*F7) | H7: =IF(A7="","",YEAR(A7))
A8: 45962 | B8: Old trip | C8: Home | D8: X | E8: 999 | F8: =IF(OR(A8="",E8=""),"",IF(A8>=Settings!$B$7,Settings!$B$6,Settings!$B$5)) | G8: =IF(F8="","",E8*F8) | H8: =IF(A8="","",YEAR(A8))
F9: =IF(OR(A9="",E9=""),"",IF(A9>=Settings!$B$7,Settings!$B$6,Settings!$B$5)) | G9: =IF(F9="","",E9*F9) | H9: =IF(A9="","",YEAR(A9))
F10: =IF(OR(A10="",E10=""),"",IF(A10>=Settings!$B$7,Settings!$B$6,Settings!$B$5)) | G10: =IF(F10="","",E10*F10) | H10: =IF(A10="","",YEAR(A10))
F11: =IF(OR(A11="",E11=""),"",IF(A11>=Settings!$B$7,Settings!$B$6,Settings!$B$5)) | G11: =IF(F11="","",E11*F11) | H11: =IF(A11="","",YEAR(A11))
F12: =IF(OR(A12="",E12=""),"",IF(A12>=Settings!$B$7,Settings!$B$6,Settings!$B$5)) | G12: =IF(F12="","",E12*F12) | H12: =IF(A12="","",YEAR(A12))
F13: =IF(OR(A13="",E13=""),"",IF(A13>=Settings!$B$7,Settings!$B$6,Settings!$B$5)) | G13: =IF(F13="","",E13*F13) | H13: =IF(A13="","",YEAR(A13))
F14: =IF(OR(A14="",E14=""),"",IF(A14>=Settings!$B$7,Settings!$B$6,Settings!$B$5)) | G14: =IF(F14="","",E14*F14) | H14: =IF(A14="","",YEAR(A14))
F15: =IF(OR(A15="",E15=""),"",IF(A15>=Settings!$B$7,Settings!$B$6,Settings!$B$5)) | G15: =IF(F15="","",E15*F15) | H15: =IF(A15="","",YEAR(A15))
F16: =IF(OR(A16="",E16=""),"",IF(A16>=Settings!$B$7,Settings!$B$6,Settings!$B$5)) | G16: =IF(F16="","",E16*F16) | H16: =IF(A16="","",YEAR(A16))
F17: =IF(OR(A17="",E17=""),"",IF(A17>=Settings!$B$7,Settings!$B$6,Settings!$B$5)) | G17: =IF(F17="","",E17*F17) | H17: =IF(A17="","",YEAR(A17))
F18: =IF(OR(A18="",E18=""),"",IF(A18>=Settings!$B$7,Settings!$B$6,Settings!$B$5)) | G18: =IF(F18="","",E18*F18) | H18: =IF(A18="","",YEAR(A18))
F19: =IF(OR(A19="",E19=""),"",IF(A19>=Settings!$B$7,Settings!$B$6,Settings!$B$5)) | G19: =IF(F19="","",E19*F19) | H19: =IF(A19="","",YEAR(A19))
F20: =IF(OR(A20="",E20=""),"",IF(A20>=Settings!$B$7,Settings!$B$6,Settings!$B$5)) | G20: =IF(F20="","",E20*F20) | H20: =IF(A20="","",YEAR(A20))
... F504: =IF(OR(A504="",E504=""),"",IF(A504>=Settings!$B$7,Settings!$B$6,Settings!$B$5)) | G504: =IF(F504="","",E504*F504) | H504: =IF(A504="","",YEAR(A504))

Sheet Deductions
A1: Deduction log
A2: Every business cost you might deduct. Receipt column = Y/N so you can find gaps.
A4: Date | B4: Item | C4: Category | D4: Amount | E4: Business use % | F4: Deductible | G4: Receipt saved? | H4: Year
A5: 46027 | B5: Laptop stand | C5: Equipment & Hardware | D5: 100 | F5: =IF(OR(A5="",D5=""),"",D5*IF(E5="",1,E5)) | G5: Y | H5: =IF(A5="","",YEAR(A5))
A6: 46062 | B6: Phone plan | C6: Internet & Phone | D6: 600 | E6: 0.5 | F6: =IF(OR(A6="",D6=""),"",D6*IF(E6="",1,E6)) | G6: N | H6: =IF(A6="","",YEAR(A6))
A7: 46082 | B7: Online course | C7: Education & Training | D7: 250 | F7: =IF(OR(A7="",D7=""),"",D7*IF(E7="",1,E7)) | G7: Y | H7: =IF(A7="","",YEAR(A7))
F8: =IF(OR(A8="",D8=""),"",D8*IF(E8="",1,E8)) | H8: =IF(A8="","",YEAR(A8))
F9: =IF(OR(A9="",D9=""),"",D9*IF(E9="",1,E9)) | H9: =IF(A9="","",YEAR(A9))
F10: =IF(OR(A10="",D10=""),"",D10*IF(E10="",1,E10)) | H10: =IF(A10="","",YEAR(A10))
F11: =IF(OR(A11="",D11=""),"",D11*IF(E11="",1,E11)) | H11: =IF(A11="","",YEAR(A11))
F12: =IF(OR(A12="",D12=""),"",D12*IF(E12="",1,E12)) | H12: =IF(A12="","",YEAR(A12))
F13: =IF(OR(A13="",D13=""),"",D13*IF(E13="",1,E13)) | H13: =IF(A13="","",YEAR(A13))
F14: =IF(OR(A14="",D14=""),"",D14*IF(E14="",1,E14)) | H14: =IF(A14="","",YEAR(A14))
F15: =IF(OR(A15="",D15=""),"",D15*IF(E15="",1,E15)) | H15: =IF(A15="","",YEAR(A15))
F16: =IF(OR(A16="",D16=""),"",D16*IF(E16="",1,E16)) | H16: =IF(A16="","",YEAR(A16))
F17: =IF(OR(A17="",D17=""),"",D17*IF(E17="",1,E17)) | H17: =IF(A17="","",YEAR(A17))
F18: =IF(OR(A18="",D18=""),"",D18*IF(E18="",1,E18)) | H18: =IF(A18="","",YEAR(A18))
F19: =IF(OR(A19="",D19=""),"",D19*IF(E19="",1,E19)) | H19: =IF(A19="","",YEAR(A19))
... F504: =IF(OR(A504="",D504=""),"",D504*IF(E504="",1,E504)) | H504: =IF(A504="","",YEAR(A504))

Sheet Home Office
A1: Home office comparison
A2: Compares the simplified method with an actual-expense estimate. Enter annual household costs.
A4: Annual household cost | B4: Amount
A5: Rent or mortgage interest | B5: 12000
A6: Utilities | B6: 1800
A7: Internet (home portion) | B7: 0
A8: Renters/home insurance | B8: 0
A9: Repairs & maintenance | B9: 0
A10: Total household costs | B10: =SUM(B5:B9)
A11: Business-use share | B11: =IF(Settings!B10=0,0,MIN(Settings!B9,Settings!B10)/Settings!B10)
A12: Actual-expense deduction (estimate) | B12: =B10*B11
A13: Simplified-method deduction (max 300 sq ft) | B13: =MIN(Settings!B9,300)*Settings!B8
A14: Better method | B14: =IF(B12>B13,"Actual expense","Simplified")
A15: Deduction to use | B15: =MAX(B12,B13)
