Workbook

Sheet Start Here
A1: Freelancer Finance Tracker - Start Here
A3: 1. Settings: set your tax year, tax rates and due dates (yellow cells).
A4: 2. Invoices: log each invoice you send (number, client, date, terms, amount).
A5: 3. Income: log every payment you receive. Enter the Invoice # and the invoice marks itself Paid / Partial.
A6: 4. Expenses: log business costs; pick a category; use Deductible % for partly personal items.
A7: 5. Clients: type your client names in column A to see who pays you and who owes you.
A8: 6. Dashboard + Tax Estimator update automatically. Move the 'tax to set aside' into savings.
A10: Yellow = you type. White = formulas, do not overwrite. Rows 5-504 on each log are pre-built.
A11: Google Sheets: File > Import > Upload > 'Replace spreadsheet'. Formulas and dropdowns carry over.
A12: Disclaimer: planning tool, not tax or legal advice. Check rates at irs.gov or with a tax professional.

Sheet Dashboard
A1: Freelancer Finance Dashboard
A2: ="Tax year "&Settings!B4&" | updated "&TEXT(TODAY(),"yyyy-mm-dd")
D3: Month | E3: Income | F3: Expenses | G3: Profit
A4: Income (YTD) | B4: =SUMIFS(Income!$E$5:$E$504,Income!$G$5:$G$504,Settings!$B$4) | D4: Jan | E4: =SUMIFS(Income!$E$5:$E$504,Income!$I$5:$I$504,1,Income!$G$5:$G$504,Settings!$B$4) | F4: =SUMIFS(Expenses!$G$5:$G$504,Expenses!$J$5:$J$504,1,Expenses!$H$5:$H$504,Settings!$B$4) | G4: =E4-F4
A5: Deductible expenses | B5: =SUMIFS(Expenses!$G$5:$G$504,Expenses!$H$5:$H$504,Settings!$B$4) | D5: Feb | E5: =SUMIFS(Income!$E$5:$E$504,Income!$I$5:$I$504,2,Income!$G$5:$G$504,Settings!$B$4) | F5: =SUMIFS(Expenses!$G$5:$G$504,Expenses!$J$5:$J$504,2,Expenses!$H$5:$H$504,Settings!$B$4) | G5: =E5-F5
A6: Net profit | B6: =B4-B5 | D6: Mar | E6: =SUMIFS(Income!$E$5:$E$504,Income!$I$5:$I$504,3,Income!$G$5:$G$504,Settings!$B$4) | F6: =SUMIFS(Expenses!$G$5:$G$504,Expenses!$J$5:$J$504,3,Expenses!$H$5:$H$504,Settings!$B$4) | G6: =E6-F6
A7: Profit margin | B7: =IF(B4=0,0,B6/B4) | D7: Apr | E7: =SUMIFS(Income!$E$5:$E$504,Income!$I$5:$I$504,4,Income!$G$5:$G$504,Settings!$B$4) | F7: =SUMIFS(Expenses!$G$5:$G$504,Expenses!$J$5:$J$504,4,Expenses!$H$5:$H$504,Settings!$B$4) | G7: =E7-F7
A8: Tax to set aside (est.) | B8: ='Tax Estimator'!H9 | D8: May | E8: =SUMIFS(Income!$E$5:$E$504,Income!$I$5:$I$504,5,Income!$G$5:$G$504,Settings!$B$4) | F8: =SUMIFS(Expenses!$G$5:$G$504,Expenses!$J$5:$J$504,5,Expenses!$H$5:$H$504,Settings!$B$4) | G8: =E8-F8
A9: Take-home after tax (est.) | B9: =B6-B8 | D9: Jun | E9: =SUMIFS(Income!$E$5:$E$504,Income!$I$5:$I$504,6,Income!$G$5:$G$504,Settings!$B$4) | F9: =SUMIFS(Expenses!$G$5:$G$504,Expenses!$J$5:$J$504,6,Expenses!$H$5:$H$504,Settings!$B$4) | G9: =E9-F9
A10: Outstanding invoices | B10: =SUM(Invoices!$H$5:$H$504) | D10: Jul | E10: =SUMIFS(Income!$E$5:$E$504,Income!$I$5:$I$504,7,Income!$G$5:$G$504,Settings!$B$4) | F10: =SUMIFS(Expenses!$G$5:$G$504,Expenses!$J$5:$J$504,7,Expenses!$H$5:$H$504,Settings!$B$4) | G10: =E10-F10
A11: Overdue amount | B11: =SUMIFS(Invoices!$H$5:$H$504,Invoices!$I$5:$I$504,"Overdue") | D11: Aug | E11: =SUMIFS(Income!$E$5:$E$504,Income!$I$5:$I$504,8,Income!$G$5:$G$504,Settings!$B$4) | F11: =SUMIFS(Expenses!$G$5:$G$504,Expenses!$J$5:$J$504,8,Expenses!$H$5:$H$504,Settings!$B$4) | G11: =E11-F11
A12: Overdue invoices (count) | B12: =COUNTIFS(Invoices!$I$5:$I$504,"Overdue") | D12: Sep | E12: =SUMIFS(Income!$E$5:$E$504,Income!$I$5:$I$504,9,Income!$G$5:$G$504,Settings!$B$4) | F12: =SUMIFS(Expenses!$G$5:$G$504,Expenses!$J$5:$J$504,9,Expenses!$H$5:$H$504,Settings!$B$4) | G12: =E12-F12
A13: Top client share of income | B13: =IF(SUM(Clients!C5:C34)=0,0,MAX(Clients!E5:E34)) | D13: Oct | E13: =SUMIFS(Income!$E$5:$E$504,Income!$I$5:$I$504,10,Income!$G$5:$G$504,Settings!$B$4) | F13: =SUMIFS(Expenses!$G$5:$G$504,Expenses!$J$5:$J$504,10,Expenses!$H$5:$H$504,Settings!$B$4) | G13: =E13-F13
D14: Nov | E14: =SUMIFS(Income!$E$5:$E$504,Income!$I$5:$I$504,11,Income!$G$5:$G$504,Settings!$B$4) | F14: =SUMIFS(Expenses!$G$5:$G$504,Expenses!$J$5:$J$504,11,Expenses!$H$5:$H$504,Settings!$B$4) | G14: =E14-F14
D15: Dec | E15: =SUMIFS(Income!$E$5:$E$504,Income!$I$5:$I$504,12,Income!$G$5:$G$504,Settings!$B$4) | F15: =SUMIFS(Expenses!$G$5:$G$504,Expenses!$J$5:$J$504,12,Expenses!$H$5:$H$504,Settings!$B$4) | G15: =E15-F15
A16: Spending by category | D16: Total | E16: =SUM(E4:E15) | F16: =SUM(F4:F15) | G16: =SUM(G4:G15)
A17: Category | B17: Deductible $
A18: =Settings!A18 | B18: =SUMIFS(Expenses!$G$5:$G$504,Expenses!$C$5:$C$504,A18,Expenses!$H$5:$H$504,Settings!$B$4)
A19: =Settings!A19 | B19: =SUMIFS(Expenses!$G$5:$G$504,Expenses!$C$5:$C$504,A19,Expenses!$H$5:$H$504,Settings!$B$4)
A20: =Settings!A20 | B20: =SUMIFS(Expenses!$G$5:$G$504,Expenses!$C$5:$C$504,A20,Expenses!$H$5:$H$504,Settings!$B$4)
A21: =Settings!A21 | B21: =SUMIFS(Expenses!$G$5:$G$504,Expenses!$C$5:$C$504,A21,Expenses!$H$5:$H$504,Settings!$B$4)
A22: =Settings!A22 | B22: =SUMIFS(Expenses!$G$5:$G$504,Expenses!$C$5:$C$504,A22,Expenses!$H$5:$H$504,Settings!$B$4)
A23: =Settings!A23 | B23: =SUMIFS(Expenses!$G$5:$G$504,Expenses!$C$5:$C$504,A23,Expenses!$H$5:$H$504,Settings!$B$4)
A24: =Settings!A24 | B24: =SUMIFS(Expenses!$G$5:$G$504,Expenses!$C$5:$C$504,A24,Expenses!$H$5:$H$504,Settings!$B$4)
A25: =Settings!A25 | B25: =SUMIFS(Expenses!$G$5:$G$504,Expenses!$C$5:$C$504,A25,Expenses!$H$5:$H$504,Settings!$B$4)
A26: =Settings!A26 | B26: =SUMIFS(Expenses!$G$5:$G$504,Expenses!$C$5:$C$504,A26,Expenses!$H$5:$H$504,Settings!$B$4)
A27: =Settings!A27 | B27: =SUMIFS(Expenses!$G$5:$G$504,Expenses!$C$5:$C$504,A27,Expenses!$H$5:$H$504,Settings!$B$4)
A28: =Settings!A28 | B28: =SUMIFS(Expenses!$G$5:$G$504,Expenses!$C$5:$C$504,A28,Expenses!$H$5:$H$504,Settings!$B$4)
A29: =Settings!A29 | B29: =SUMIFS(Expenses!$G$5:$G$504,Expenses!$C$5:$C$504,A29,Expenses!$H$5:$H$504,Settings!$B$4)
... A31: =Settings!A31 | B31: =SUMIFS(Expenses!$G$5:$G$504,Expenses!$C$5:$C$504,A31,Expenses!$H$5:$H$504,Settings!$B$4)

Sheet Settings
A1: Settings
A2: Yellow cells are yours to edit. Everything else calculates.
A4: Tax year | B4: 2026 | D4: Notes
A5: Self-employment tax rate | B5: 0.153 | D5: Tax periods follow the IRS estimated-tax schedule, not calendar quarters:
A6: Net earnings factor (SE base) | B6: 0.9235 | D6: P1 Jan-Mar, P2 Apr-May, P3 Jun-Aug, P4 Sep-Dec.
A7: Est. income tax rate on profit | B7: 0.12 | D7: Default rates are placeholders - set them with your accountant or IRS Form 1040-ES.
A8: State / local tax rate on profit | B8: 0.04 | D8: This workbook gives estimates for planning. It is not tax advice.
A9: Extra cushion on tax set-aside | B9: 0.05
A11: Estimated-tax payment due dates (edit if the IRS shifts them)
A12: Period 1 (Jan-Mar) | B12: 46127
A13: Period 2 (Apr-May) | B13: 46188
A14: Period 3 (Jun-Aug) | B14: 46280
A15: Period 4 (Sep-Dec) | B15: 46405
A17: Expense categories (edit the list; dropdown on Expenses uses it)
A18: Software & Subscriptions
A19: Equipment & Hardware
A20: Home Office
A21: Internet & Phone
A22: Marketing & Advertising
A23: Professional Services
A24: Education & Training
A25: Travel
A26: Meals (50%)
A27: Contractors & Subcontractors
A28: Bank & Payment Fees
... A31: Other

Sheet Income
A1: Income log
A2: One row per payment received. Put the Invoice # to auto-reconcile the Invoices sheet.
A4: Date received | B4: Client | C4: Invoice # | D4: Description | E4: Amount | F4: Payment method | G4: Year | H4: Tax period | I4: Month
G5: =IF(A5="","",YEAR(A5)) | H5: =IF(A5="","",IF(MONTH(A5)<=3,1,IF(MONTH(A5)<=5,2,IF(MONTH(A5)<=8,3,4)))) | I5: =IF(A5="","",MONTH(A5))
G6: =IF(A6="","",YEAR(A6)) | H6: =IF(A6="","",IF(MONTH(A6)<=3,1,IF(MONTH(A6)<=5,2,IF(MONTH(A6)<=8,3,4)))) | I6: =IF(A6="","",MONTH(A6))
G7: =IF(A7="","",YEAR(A7)) | H7: =IF(A7="","",IF(MONTH(A7)<=3,1,IF(MONTH(A7)<=5,2,IF(MONTH(A7)<=8,3,4)))) | I7: =IF(A7="","",MONTH(A7))
G8: =IF(A8="","",YEAR(A8)) | H8: =IF(A8="","",IF(MONTH(A8)<=3,1,IF(MONTH(A8)<=5,2,IF(MONTH(A8)<=8,3,4)))) | I8: =IF(A8="","",MONTH(A8))
G9: =IF(A9="","",YEAR(A9)) | H9: =IF(A9="","",IF(MONTH(A9)<=3,1,IF(MONTH(A9)<=5,2,IF(MONTH(A9)<=8,3,4)))) | I9: =IF(A9="","",MONTH(A9))
G10: =IF(A10="","",YEAR(A10)) | H10: =IF(A10="","",IF(MONTH(A10)<=3,1,IF(MONTH(A10)<=5,2,IF(MONTH(A10)<=8,3,4)))) | I10: =IF(A10="","",MONTH(A10))
G11: =IF(A11="","",YEAR(A11)) | H11: =IF(A11="","",IF(MONTH(A11)<=3,1,IF(MONTH(A11)<=5,2,IF(MONTH(A11)<=8,3,4)))) | I11: =IF(A11="","",MONTH(A11))
G12: =IF(A12="","",YEAR(A12)) | H12: =IF(A12="","",IF(MONTH(A12)<=3,1,IF(MONTH(A12)<=5,2,IF(MONTH(A12)<=8,3,4)))) | I12: =IF(A12="","",MONTH(A12))
G13: =IF(A13="","",YEAR(A13)) | H13: =IF(A13="","",IF(MONTH(A13)<=3,1,IF(MONTH(A13)<=5,2,IF(MONTH(A13)<=8,3,4)))) | I13: =IF(A13="","",MONTH(A13))
G14: =IF(A14="","",YEAR(A14)) | H14: =IF(A14="","",IF(MONTH(A14)<=3,1,IF(MONTH(A14)<=5,2,IF(MONTH(A14)<=8,3,4)))) | I14: =IF(A14="","",MONTH(A14))
G15: =IF(A15="","",YEAR(A15)) | H15: =IF(A15="","",IF(MONTH(A15)<=3,1,IF(MONTH(A15)<=5,2,IF(MONTH(A15)<=8,3,4)))) | I15: =IF(A15="","",MONTH(A15))
G16: =IF(A16="","",YEAR(A16)) | H16: =IF(A16="","",IF(MONTH(A16)<=3,1,IF(MONTH(A16)<=5,2,IF(MONTH(A16)<=8,3,4)))) | I16: =IF(A16="","",MONTH(A16))
... G504: =IF(A504="","",YEAR(A504)) | H504: =IF(A504="","",IF(MONTH(A504)<=3,1,IF(MONTH(A504)<=5,2,IF(MONTH(A504)<=8,3,4)))) | I504: =IF(A504="","",MONTH(A504))

Sheet Expenses
A1: Expense log
A2: Deductible % lets you log partial-use items (phone 50%, meals 50%). Leave blank for 100%.
A4: Date | B4: Vendor | C4: Category | D4: Description | E4: Amount paid | F4: Deductible % | G4: Deductible amount | H4: Year | I4: Tax period | J4: Month
G5: =IF(OR(A5="",E5=""),"",E5*IF(F5="",1,F5)) | H5: =IF(A5="","",YEAR(A5)) | I5: =IF(A5="","",IF(MONTH(A5)<=3,1,IF(MONTH(A5)<=5,2,IF(MONTH(A5)<=8,3,4)))) | J5: =IF(A5="","",MONTH(A5))
G6: =IF(OR(A6="",E6=""),"",E6*IF(F6="",1,F6)) | H6: =IF(A6="","",YEAR(A6)) | I6: =IF(A6="","",IF(MONTH(A6)<=3,1,IF(MONTH(A6)<=5,2,IF(MONTH(A6)<=8,3,4)))) | J6: =IF(A6="","",MONTH(A6))
G7: =IF(OR(A7="",E7=""),"",E7*IF(F7="",1,F7)) | H7: =IF(A7="","",YEAR(A7)) | I7: =IF(A7="","",IF(MONTH(A7)<=3,1,IF(MONTH(A7)<=5,2,IF(MONTH(A7)<=8,3,4)))) | J7: =IF(A7="","",MONTH(A7))
G8: =IF(OR(A8="",E8=""),"",E8*IF(F8="",1,F8)) | H8: =IF(A8="","",YEAR(A8)) | I8: =IF(A8="","",IF(MONTH(A8)<=3,1,IF(MONTH(A8)<=5,2,IF(MONTH(A8)<=8,3,4)))) | J8: =IF(A8="","",MONTH(A8))
G9: =IF(OR(A9="",E9=""),"",E9*IF(F9="",1,F9)) | H9: =IF(A9="","",YEAR(A9)) | I9: =IF(A9="","",IF(MONTH(A9)<=3,1,IF(MONTH(A9)<=5,2,IF(MONTH(A9)<=8,3,4)))) | J9: =IF(A9="","",MONTH(A9))
G10: =IF(OR(A10="",E10=""),"",E10*IF(F10="",1,F10)) | H10: =IF(A10="","",YEAR(A10)) | I10: =IF(A10="","",IF(MONTH(A10)<=3,1,IF(MONTH(A10)<=5,2,IF(MONTH(A10)<=8,3,4)))) | J10: =IF(A10="","",MONTH(A10))
G11: =IF(OR(A11="",E11=""),"",E11*IF(F11="",1,F11)) | H11: =IF(A11="","",YEAR(A11)) | I11: =IF(A11="","",IF(MONTH(A11)<=3,1,IF(MONTH(A11)<=5,2,IF(MONTH(A11)<=8,3,4)))) | J11: =IF(A11="","",MONTH(A11))
G12: =IF(OR(A12="",E12=""),"",E12*IF(F12="",1,F12)) | H12: =IF(A12="","",YEAR(A12)) | I12: =IF(A12="","",IF(MONTH(A12)<=3,1,IF(MONTH(A12)<=5,2,IF(MONTH(A12)<=8,3,4)))) | J12: =IF(A12="","",MONTH(A12))
G13: =IF(OR(A13="",E13=""),"",E13*IF(F13="",1,F13)) | H13: =IF(A13="","",YEAR(A13)) | I13: =IF(A13="","",IF(MONTH(A13)<=3,1,IF(MONTH(A13)<=5,2,IF(MONTH(A13)<=8,3,4)))) | J13: =IF(A13="","",MONTH(A13))
G14: =IF(OR(A14="",E14=""),"",E14*IF(F14="",1,F14)) | H14: =IF(A14="","",YEAR(A14)) | I14: =IF(A14="","",IF(MONTH(A14)<=3,1,IF(MONTH(A14)<=5,2,IF(MONTH(A14)<=8,3,4)))) | J14: =IF(A14="","",MONTH(A14))
G15: =IF(OR(A15="",E15=""),"",E15*IF(F15="",1,F15)) | H15: =IF(A15="","",YEAR(A15)) | I15: =IF(A15="","",IF(MONTH(A15)<=3,1,IF(MONTH(A15)<=5,2,IF(MONTH(A15)<=8,3,4)))) | J15: =IF(A15="","",MONTH(A15))
G16: =IF(OR(A16="",E16=""),"",E16*IF(F16="",1,F16)) | H16: =IF(A16="","",YEAR(A16)) | I16: =IF(A16="","",IF(MONTH(A16)<=3,1,IF(MONTH(A16)<=5,2,IF(MONTH(A16)<=8,3,4)))) | J16: =IF(A16="","",MONTH(A16))
... G504: =IF(OR(A504="",E504=""),"",E504*IF(F504="",1,F504)) | H504: =IF(A504="","",YEAR(A504)) | I504: =IF(A504="","",IF(MONTH(A504)<=3,1,IF(MONTH(A504)<=5,2,IF(MONTH(A504)<=8,3,4)))) | J504: =IF(A504="","",MONTH(A504))

Sheet Invoices
A1: Invoice tracker
A2: Enter the invoice details. Paid amount fills itself from the Income log (matched by Invoice #).
A4: Invoice # | B4: Client | C4: Issue date | D4: Terms (days) | E4: Due date | F4: Amount | G4: Paid to date | H4: Balance | I4: Status | J4: Days overdue
E5: =IF(OR(C5="",D5=""),"",C5+D5) | G5: =IF(A5="","",SUMIFS(Income!$E$5:$E$504,Income!$C$5:$C$504,A5)) | H5: =IF(OR(A5="",F5=""),"",F5-G5) | I5: =IF(OR(A5="",F5=""),"",IF(H5<=0.004,"Paid",IF(AND(E5<>"",TODAY()>E5),"Overdue",IF(G5>0,"Partial","Open")))) | J5: =IF(I5="Overdue",TODAY()-E5,"")
E6: =IF(OR(C6="",D6=""),"",C6+D6) | G6: =IF(A6="","",SUMIFS(Income!$E$5:$E$504,Income!$C$5:$C$504,A6)) | H6: =IF(OR(A6="",F6=""),"",F6-G6) | I6: =IF(OR(A6="",F6=""),"",IF(H6<=0.004,"Paid",IF(AND(E6<>"",TODAY()>E6),"Overdue",IF(G6>0,"Partial","Open")))) | J6: =IF(I6="Overdue",TODAY()-E6,"")
E7: =IF(OR(C7="",D7=""),"",C7+D7) | G7: =IF(A7="","",SUMIFS(Income!$E$5:$E$504,Income!$C$5:$C$504,A7)) | H7: =IF(OR(A7="",F7=""),"",F7-G7) | I7: =IF(OR(A7="",F7=""),"",IF(H7<=0.004,"Paid",IF(AND(E7<>"",TODAY()>E7),"Overdue",IF(G7>0,"Partial","Open")))) | J7: =IF(I7="Overdue",TODAY()-E7,"")
E8: =IF(OR(C8="",D8=""),"",C8+D8) | G8: =IF(A8="","",SUMIFS(Income!$E$5:$E$504,Income!$C$5:$C$504,A8)) | H8: =IF(OR(A8="",F8=""),"",F8-G8) | I8: =IF(OR(A8="",F8=""),"",IF(H8<=0.004,"Paid",IF(AND(E8<>"",TODAY()>E8),"Overdue",IF(G8>0,"Partial","Open")))) | J8: =IF(I8="Overdue",TODAY()-E8,"")
E9: =IF(OR(C9="",D9=""),"",C9+D9) | G9: =IF(A9="","",SUMIFS(Income!$E$5:$E$504,Income!$C$5:$C$504,A9)) | H9: =IF(OR(A9="",F9=""),"",F9-G9) | I9: =IF(OR(A9="",F9=""),"",IF(H9<=0.004,"Paid",IF(AND(E9<>"",TODAY()>E9),"Overdue",IF(G9>0,"Partial","Open")))) | J9: =IF(I9="Overdue",TODAY()-E9,"")
E10: =IF(OR(C10="",D10=""),"",C10+D10) | G10: =IF(A10="","",SUMIFS(Income!$E$5:$E$504,Income!$C$5:$C$504,A10)) | H10: =IF(OR(A10="",F10=""),"",F10-G10) | I10: =IF(OR(A10="",F10=""),"",IF(H10<=0.004,"Paid",IF(AND(E10<>"",TODAY()>E10),"Overdue",IF(G10>0,"Partial","Open")))) | J10: =IF(I10="Overdue",TODAY()-E10,"")
E11: =IF(OR(C11="",D11=""),"",C11+D11) | G11: =IF(A11="","",SUMIFS(Income!$E$5:$E$504,Income!$C$5:$C$504,A11)) | H11: =IF(OR(A11="",F11=""),"",F11-G11) | I11: =IF(OR(A11="",F11=""),"",IF(H11<=0.004,"Paid",IF(AND(E11<>"",TODAY()>E11),"Overdue",IF(G11>0,"Partial","Open")))) | J11: =IF(I11="Overdue",TODAY()-E11,"")
E12: =IF(OR(C12="",D12=""),"",C12+D12) | G12: =IF(A12="","",SUMIFS(Income!$E$5:$E$504,Income!$C$5:$C$504,A12)) | H12: =IF(OR(A12="",F12=""),"",F12-G12) | I12: =IF(OR(A12="",F12=""),"",IF(H12<=0.004,"Paid",IF(AND(E12<>"",TODAY()>E12),"Overdue",IF(G12>0,"Partial","Open")))) | J12: =IF(I12="Overdue",TODAY()-E12,"")
E13: =IF(OR(C13="",D13=""),"",C13+D13) | G13: =IF(A13="","",SUMIFS(Income!$E$5:$E$504,Income!$C$5:$C$504,A13)) | H13: =IF(OR(A13="",F13=""),"",F13-G13) | I13: =IF(OR(A13="",F13=""),"",IF(H13<=0.004,"Paid",IF(AND(E13<>"",TODAY()>E13),"Overdue",IF(G13>0,"Partial","Open")))) | J13: =IF(I13="Overdue",TODAY()-E13,"")
E14: =IF(OR(C14="",D14=""),"",C14+D14) | G14: =IF(A14="","",SUMIFS(Income!$E$5:$E$504,Income!$C$5:$C$504,A14)) | H14: =IF(OR(A14="",F14=""),"",F14-G14) | I14: =IF(OR(A14="",F14=""),"",IF(H14<=0.004,"Paid",IF(AND(E14<>"",TODAY()>E14),"Overdue",IF(G14>0,"Partial","Open")))) | J14: =IF(I14="Overdue",TODAY()-E14,"")
E15: =IF(OR(C15="",D15=""),"",C15+D15) | G15: =IF(A15="","",SUMIFS(Income!$E$5:$E$504,Income!$C$5:$C$504,A15)) | H15: =IF(OR(A15="",F15=""),"",F15-G15) | I15: =IF(OR(A15="",F15=""),"",IF(H15<=0.004,"Paid",IF(AND(E15<>"",TODAY()>E15),"Overdue",IF(G15>0,"Partial","Open")))) | J15: =IF(I15="Overdue",TODAY()-E15,"")
E16: =IF(OR(C16="",D16=""),"",C16+D16) | G16: =IF(A16="","",SUMIFS(Income!$E$5:$E$504,Income!$C$5:$C$504,A16)) | H16: =IF(OR(A16="",F16=""),"",F16-G16) | I16: =IF(OR(A16="",F16=""),"",IF(H16<=0.004,"Paid",IF(AND(E16<>"",TODAY()>E16),"Overdue",IF(G16>0,"Partial","Open")))) | J16: =IF(I16="Overdue",TODAY()-E16,"")
... E504: =IF(OR(C504="",D504=""),"",C504+D504) | G504: =IF(A504="","",SUMIFS(Income!$E$5:$E$504,Income!$C$5:$C$504,A504)) | H504: =IF(OR(A504="",F504=""),"",F504-G504) | I504: =IF(OR(A504="",F504=""),"",IF(H504<=0.004,"Paid",IF(AND(E504<>"",TODAY()>E504),"Overdue",IF(G504>0,"Partial","Open")))) | J504: =IF(I504="Overdue",TODAY()-E504,"")

Sheet Clients
A1: Client summary
A2: Type client names in column A (exactly as in Income/Invoices). Totals are for the tax year in Settings.
A4: Client | B4: Invoiced | C4: Received | D4: Outstanding | E4: % of income | F4: Invoices
B5: =IF(A5="","",SUMIFS(Invoices!$F$5:$F$504,Invoices!$B$5:$B$504,A5,Invoices!$C$5:$C$504,">="&DATE(Settings!$B$4,1,1),Invoices!$C$5:$C$504,"<="&DATE(Settings!$B$4,12,31))) | C5: =IF(A5="","",SUMIFS(Income!$E$5:$E$504,Income!$B$5:$B$504,A5,Income!$G$5:$G$504,Settings!$B$4)) | D5: =IF(A5="","",SUMIFS(Invoices!$H$5:$H$504,Invoices!$B$5:$B$504,A5)) | E5: =IF(OR(A5="",SUM($C$5:$C$34)=0),"",C5/SUM($C$5:$C$34)) | F5: =IF(A5="","",COUNTIFS(Invoices!$B$5:$B$504,A5))
B6: =IF(A6="","",SUMIFS(Invoices!$F$5:$F$504,Invoices!$B$5:$B$504,A6,Invoices!$C$5:$C$504,">="&DATE(Settings!$B$4,1,1),Invoices!$C$5:$C$504,"<="&DATE(Settings!$B$4,12,31))) | C6: =IF(A6="","",SUMIFS(Income!$E$5:$E$504,Income!$B$5:$B$504,A6,Income!$G$5:$G$504,Settings!$B$4)) | D6: =IF(A6="","",SUMIFS(Invoices!$H$5:$H$504,Invoices!$B$5:$B$504,A6)) | E6: =IF(OR(A6="",SUM($C$5:$C$34)=0),"",C6/SUM($C$5:$C$34)) | F6: =IF(A6="","",COUNTIFS(Invoices!$B$5:$B$504,A6))
B7: =IF(A7="","",SUMIFS(Invoices!$F$5:$F$504,Invoices!$B$5:$B$504,A7,Invoices!$C$5:$C$504,">="&DATE(Settings!$B$4,1,1),Invoices!$C$5:$C$504,"<="&DATE(Settings!$B$4,12,31))) | C7: =IF(A7="","",SUMIFS(Income!$E$5:$E$504,Income!$B$5:$B$504,A7,Income!$G$5:$G$504,Settings!$B$4)) | D7: =IF(A7="","",SUMIFS(Invoices!$H$5:$H$504,Invoices!$B$5:$B$504,A7)) | E7: =IF(OR(A7="",SUM($C$5:$C$34)=0),"",C7/SUM($C$5:$C$34)) | F7: =IF(A7="","",COUNTIFS(Invoices!$B$5:$B$504,A7))
B8: =IF(A8="","",SUMIFS(Invoices!$F$5:$F$504,Invoices!$B$5:$B$504,A8,Invoices!$C$5:$C$504,">="&DATE(Settings!$B$4,1,1),Invoices!$C$5:$C$504,"<="&DATE(Settings!$B$4,12,31))) | C8: =IF(A8="","",SUMIFS(Income!$E$5:$E$504,Income!$B$5:$B$504,A8,Income!$G$5:$G$504,Settings!$B$4)) | D8: =IF(A8="","",SUMIFS(Invoices!$H$5:$H$504,Invoices!$B$5:$B$504,A8)) | E8: =IF(OR(A8="",SUM($C$5:$C$34)=0),"",C8/SUM($C$5:$C$34)) | F8: =IF(A8="","",COUNTIFS(Invoices!$B$5:$B$504,A8))
B9: =IF(A9="","",SUMIFS(Invoices!$F$5:$F$504,Invoices!$B$5:$B$504,A9,Invoices!$C$5:$C$504,">="&DATE(Settings!$B$4,1,1),Invoices!$C$5:$C$504,"<="&DATE(Settings!$B$4,12,31))) | C9: =IF(A9="","",SUMIFS(Income!$E$5:$E$504,Income!$B$5:$B$504,A9,Income!$G$5:$G$504,Settings!$B$4)) | D9: =IF(A9="","",SUMIFS(Invoices!$H$5:$H$504,Invoices!$B$5:$B$504,A9)) | E9: =IF(OR(A9="",SUM($C$5:$C$34)=0),"",C9/SUM($C$5:$C$34)) | F9: =IF(A9="","",COUNTIFS(Invoices!$B$5:$B$504,A9))
B10: =IF(A10="","",SUMIFS(Invoices!$F$5:$F$504,Invoices!$B$5:$B$504,A10,Invoices!$C$5:$C$504,">="&DATE(Settings!$B$4,1,1),Invoices!$C$5:$C$504,"<="&DATE(Settings!$B$4,12,31))) | C10: =IF(A10="","",SUMIFS(Income!$E$5:$E$504,Income!$B$5:$B$504,A10,Income!$G$5:$G$504,Settings!$B$4)) | D10: =IF(A10="","",SUMIFS(Invoices!$H$5:$H$504,Invoices!$B$5:$B$504,A10)) | E10: =IF(OR(A10="",SUM($C$5:$C$34)=0),"",C10/SUM($C$5:$C$34)) | F10: =IF(A10="","",COUNTIFS(Invoices!$B$5:$B$504,A10))
B11: =IF(A11="","",SUMIFS(Invoices!$F$5:$F$504,Invoices!$B$5:$B$504,A11,Invoices!$C$5:$C$504,">="&DATE(Settings!$B$4,1,1),Invoices!$C$5:$C$504,"<="&DATE(Settings!$B$4,12,31))) | C11: =IF(A11="","",SUMIFS(Income!$E$5:$E$504,Income!$B$5:$B$504,A11,Income!$G$5:$G$504,Settings!$B$4)) | D11: =IF(A11="","",SUMIFS(Invoices!$H$5:$H$504,Invoices!$B$5:$B$504,A11)) | E11: =IF(OR(A11="",SUM($C$5:$C$34)=0),"",C11/SUM($C$5:$C$34)) | F11: =IF(A11="","",COUNTIFS(Invoices!$B$5:$B$504,A11))
B12: =IF(A12="","",SUMIFS(Invoices!$F$5:$F$504,Invoices!$B$5:$B$504,A12,Invoices!$C$5:$C$504,">="&DATE(Settings!$B$4,1,1),Invoices!$C$5:$C$504,"<="&DATE(Settings!$B$4,12,31))) | C12: =IF(A12="","",SUMIFS(Income!$E$5:$E$504,Income!$B$5:$B$504,A12,Income!$G$5:$G$504,Settings!$B$4)) | D12: =IF(A12="","",SUMIFS(Invoices!$H$5:$H$504,Invoices!$B$5:$B$504,A12)) | E12: =IF(OR(A12="",SUM($C$5:$C$34)=0),"",C12/SUM($C$5:$C$34)) | F12: =IF(A12="","",COUNTIFS(Invoices!$B$5:$B$504,A12))
B13: =IF(A13="","",SUMIFS(Invoices!$F$5:$F$504,Invoices!$B$5:$B$504,A13,Invoices!$C$5:$C$504,">="&DATE(Settings!$B$4,1,1),Invoices!$C$5:$C$504,"<="&DATE(Settings!$B$4,12,31))) | C13: =IF(A13="","",SUMIFS(Income!$E$5:$E$504,Income!$B$5:$B$504,A13,Income!$G$5:$G$504,Settings!$B$4)) | D13: =IF(A13="","",SUMIFS(Invoices!$H$5:$H$504,Invoices!$B$5:$B$504,A13)) | E13: =IF(OR(A13="",SUM($C$5:$C$34)=0),"",C13/SUM($C$5:$C$34)) | F13: =IF(A13="","",COUNTIFS(Invoices!$B$5:$B$504,A13))
B14: =IF(A14="","",SUMIFS(Invoices!$F$5:$F$504,Invoices!$B$5:$B$504,A14,Invoices!$C$5:$C$504,">="&DATE(Settings!$B$4,1,1),Invoices!$C$5:$C$504,"<="&DATE(Settings!$B$4,12,31))) | C14: =IF(A14="","",SUMIFS(Income!$E$5:$E$504,Income!$B$5:$B$504,A14,Income!$G$5:$G$504,Settings!$B$4)) | D14: =IF(A14="","",SUMIFS(Invoices!$H$5:$H$504,Invoices!$B$5:$B$504,A14)) | E14: =IF(OR(A14="",SUM($C$5:$C$34)=0),"",C14/SUM($C$5:$C$34)) | F14: =IF(A14="","",COUNTIFS(Invoices!$B$5:$B$504,A14))
B15: =IF(A15="","",SUMIFS(Invoices!$F$5:$F$504,Invoices!$B$5:$B$504,A15,Invoices!$C$5:$C$504,">="&DATE(Settings!$B$4,1,1),Invoices!$C$5:$C$504,"<="&DATE(Settings!$B$4,12,31))) | C15: =IF(A15="","",SUMIFS(Income!$E$5:$E$504,Income!$B$5:$B$504,A15,Income!$G$5:$G$504,Settings!$B$4)) | D15: =IF(A15="","",SUMIFS(Invoices!$H$5:$H$504,Invoices!$B$5:$B$504,A15)) | E15: =IF(OR(A15="",SUM($C$5:$C$34)=0),"",C15/SUM($C$5:$C$34)) | F15: =IF(A15="","",COUNTIFS(Invoices!$B$5:$B$504,A15))
B16: =IF(A16="","",SUMIFS(Invoices!$F$5:$F$504,Invoices!$B$5:$B$504,A16,Invoices!$C$5:$C$504,">="&DATE(Settings!$B$4,1,1),Invoices!$C$5:$C$504,"<="&DATE(Settings!$B$4,12,31))) | C16: =IF(A16="","",SUMIFS(Income!$E$5:$E$504,Income!$B$5:$B$504,A16,Income!$G$5:$G$504,Settings!$B$4)) | D16: =IF(A16="","",SUMIFS(Invoices!$H$5:$H$504,Invoices!$B$5:$B$504,A16)) | E16: =IF(OR(A16="",SUM($C$5:$C$34)=0),"",C16/SUM($C$5:$C$34)) | F16: =IF(A16="","",COUNTIFS(Invoices!$B$5:$B$504,A16))
... B34: =IF(A34="","",SUMIFS(Invoices!$F$5:$F$504,Invoices!$B$5:$B$504,A34,Invoices!$C$5:$C$504,">="&DATE(Settings!$B$4,1,1),Invoices!$C$5:$C$504,"<="&DATE(Settings!$B$4,12,31))) | C34: =IF(A34="","",SUMIFS(Income!$E$5:$E$504,Income!$B$5:$B$504,A34,Income!$G$5:$G$504,Settings!$B$4)) | D34: =IF(A34="","",SUMIFS(Invoices!$H$5:$H$504,Invoices!$B$5:$B$504,A34)) | E34: =IF(OR(A34="",SUM($C$5:$C$34)=0),"",C34/SUM($C$5:$C$34)) | F34: =IF(A34="","",COUNTIFS(Invoices!$B$5:$B$504,A34))

Sheet Tax Estimator
A1: Estimated tax set-aside
A2: Per IRS payment period for the tax year in Settings. Planning estimate only.
A4: Period | B4: Due date | C4: Income | D4: Deductible expenses | E4: Net profit | F4: SE tax | G4: Income + state tax | H4: Total to set aside | I4: Cumulative set-aside
A5: P1 Jan-Mar | B5: =Settings!B12 | C5: =SUMIFS(Income!$E$5:$E$504,Income!$H$5:$H$504,1,Income!$G$5:$G$504,Settings!$B$4) | D5: =SUMIFS(Expenses!$G$5:$G$504,Expenses!$I$5:$I$504,1,Expenses!$H$5:$H$504,Settings!$B$4) | E5: =C5-D5 | F5: =MAX(0,E5)*Settings!$B$6*Settings!$B$5 | G5: =MAX(0,E5-F5/2)*(Settings!$B$7+Settings!$B$8) | H5: =(F5+G5)*(1+Settings!$B$9) | I5: =SUM($H$5:H5)
A6: P2 Apr-May | B6: =Settings!B13 | C6: =SUMIFS(Income!$E$5:$E$504,Income!$H$5:$H$504,2,Income!$G$5:$G$504,Settings!$B$4) | D6: =SUMIFS(Expenses!$G$5:$G$504,Expenses!$I$5:$I$504,2,Expenses!$H$5:$H$504,Settings!$B$4) | E6: =C6-D6 | F6: =MAX(0,E6)*Settings!$B$6*Settings!$B$5 | G6: =MAX(0,E6-F6/2)*(Settings!$B$7+Settings!$B$8) | H6: =(F6+G6)*(1+Settings!$B$9) | I6: =SUM($H$5:H6)
A7: P3 Jun-Aug | B7: =Settings!B14 | C7: =SUMIFS(Income!$E$5:$E$504,Income!$H$5:$H$504,3,Income!$G$5:$G$504,Settings!$B$4) | D7: =SUMIFS(Expenses!$G$5:$G$504,Expenses!$I$5:$I$504,3,Expenses!$H$5:$H$504,Settings!$B$4) | E7: =C7-D7 | F7: =MAX(0,E7)*Settings!$B$6*Settings!$B$5 | G7: =MAX(0,E7-F7/2)*(Settings!$B$7+Settings!$B$8) | H7: =(F7+G7)*(1+Settings!$B$9) | I7: =SUM($H$5:H7)
A8: P4 Sep-Dec | B8: =Settings!B15 | C8: =SUMIFS(Income!$E$5:$E$504,Income!$H$5:$H$504,4,Income!$G$5:$G$504,Settings!$B$4) | D8: =SUMIFS(Expenses!$G$5:$G$504,Expenses!$I$5:$I$504,4,Expenses!$H$5:$H$504,Settings!$B$4) | E8: =C8-D8 | F8: =MAX(0,E8)*Settings!$B$6*Settings!$B$5 | G8: =MAX(0,E8-F8/2)*(Settings!$B$7+Settings!$B$8) | H8: =(F8+G8)*(1+Settings!$B$9) | I8: =SUM($H$5:H8)
A9: Year total | C9: =SUM(C5:C8) | D9: =SUM(D5:D8) | E9: =SUM(E5:E8) | F9: =SUM(F5:F8) | G9: =SUM(G5:G8) | H9: =SUM(H5:H8)
A11: How it works: SE tax = net profit x 92.35% x 15.3%. Income tax = (profit - half of SE tax) x your income + state rates. Then your cushion is added.
A12: Move the 'Total to set aside' amount into a separate savings account the week each payment lands.
