Workbook

Sheet Rate Calculator
A1: Freelance Rate Calculator
A2: Work backwards from the income you want to the hourly and day rate you must charge.
A4: Desired annual take-home pay | B4: 60000
A5: Annual business expenses | B5: 6000
A6: Annual health insurance / retirement you fund | B6: 5000
A7: Estimated total tax rate (SE + income + state) | B7: 0.3
A8: Weeks worked per year (after holidays, vacation) | B8: 46
A9: Hours per week you work | B9: 40
A10: Billable share of working hours | B10: 0.6
A11: Profit buffer | B11: 0.1
A12: Results
A13: Revenue needed before tax | B13: =(B4+B6)/(1-B7)+B5
A14: Revenue needed incl. profit buffer | B14: =B13*(1+B11)
A15: Billable hours per year | B15: =B8*B9*B10
A16: MINIMUM HOURLY RATE | B16: =IF(B15=0,0,B14/B15)
A17: Day rate (7 billable hrs) | B17: =B16*7
A18: Project rate for 20 hours | B18: =B16*20
A19: Monthly revenue target | B19: =B14/12
A21: Tip: billable share is usually 50-70% for freelancers - admin, sales and invoicing eat the rest.

Sheet Project Profitability
A1: Project profitability
A2: Quote vs reality. Find out which clients and project types actually pay you well.
A4: Project | B4: Client | C4: Quoted price | D4: Est. hours | E4: Actual hours | F4: Direct costs | G4: Profit | H4: Effective hourly | I4: Target hourly | J4: vs target | K4: Verdict | M4: Totals
A5: Logo pack | B5: Acme Co | C5: 1500 | D5: 15 | E5: 20 | F5: 50 | G5: =IF(C5="","",C5-IF(F5="",0,F5)) | H5: =IF(OR(C5="",E5="",E5=0),"",G5/E5) | I5: =IF(C5="","",'Rate Calculator'!$B$16) | J5: =IF(OR(H5="",I5=""),"",H5-I5) | K5: =IF(H5="","",IF(H5>=I5,"On target",IF(H5>=0.7*I5,"Underpriced","Money loser"))) | M5: Revenue | N5: =SUM(C5:C204)
A6: Website | B6: Birch Studio | C6: 4000 | D6: 40 | E6: 38 | F6: 200 | G6: =IF(C6="","",C6-IF(F6="",0,F6)) | H6: =IF(OR(C6="",E6="",E6=0),"",G6/E6) | I6: =IF(C6="","",'Rate Calculator'!$B$16) | J6: =IF(OR(H6="",I6=""),"",H6-I6) | K6: =IF(H6="","",IF(H6>=I6,"On target",IF(H6>=0.7*I6,"Underpriced","Money loser"))) | M6: Profit | N6: =SUM(G5:G204)
A7: Newsletter | B7: Cobalt Ltd | C7: 600 | D7: 6 | E7: 16 | F7: 0 | G7: =IF(C7="","",C7-IF(F7="",0,F7)) | H7: =IF(OR(C7="",E7="",E7=0),"",G7/E7) | I7: =IF(C7="","",'Rate Calculator'!$B$16) | J7: =IF(OR(H7="",I7=""),"",H7-I7) | K7: =IF(H7="","",IF(H7>=I7,"On target",IF(H7>=0.7*I7,"Underpriced","Money loser"))) | M7: Hours | N7: =SUM(E5:E204)
G8: =IF(C8="","",C8-IF(F8="",0,F8)) | H8: =IF(OR(C8="",E8="",E8=0),"",G8/E8) | I8: =IF(C8="","",'Rate Calculator'!$B$16) | J8: =IF(OR(H8="",I8=""),"",H8-I8) | K8: =IF(H8="","",IF(H8>=I8,"On target",IF(H8>=0.7*I8,"Underpriced","Money loser"))) | M8: Blended hourly | N8: =IF(N7=0,0,SUMIFS(G5:G204,E5:E204,">0")/N7)
G9: =IF(C9="","",C9-IF(F9="",0,F9)) | H9: =IF(OR(C9="",E9="",E9=0),"",G9/E9) | I9: =IF(C9="","",'Rate Calculator'!$B$16) | J9: =IF(OR(H9="",I9=""),"",H9-I9) | K9: =IF(H9="","",IF(H9>=I9,"On target",IF(H9>=0.7*I9,"Underpriced","Money loser"))) | M9: Hours over estimate | N9: =SUMPRODUCT((D5:D204<>"")*(E5:E204<>"")*(E5:E204-D5:D204))
G10: =IF(C10="","",C10-IF(F10="",0,F10)) | H10: =IF(OR(C10="",E10="",E10=0),"",G10/E10) | I10: =IF(C10="","",'Rate Calculator'!$B$16) | J10: =IF(OR(H10="",I10=""),"",H10-I10) | K10: =IF(H10="","",IF(H10>=I10,"On target",IF(H10>=0.7*I10,"Underpriced","Money loser")))
G11: =IF(C11="","",C11-IF(F11="",0,F11)) | H11: =IF(OR(C11="",E11="",E11=0),"",G11/E11) | I11: =IF(C11="","",'Rate Calculator'!$B$16) | J11: =IF(OR(H11="",I11=""),"",H11-I11) | K11: =IF(H11="","",IF(H11>=I11,"On target",IF(H11>=0.7*I11,"Underpriced","Money loser")))
G12: =IF(C12="","",C12-IF(F12="",0,F12)) | H12: =IF(OR(C12="",E12="",E12=0),"",G12/E12) | I12: =IF(C12="","",'Rate Calculator'!$B$16) | J12: =IF(OR(H12="",I12=""),"",H12-I12) | K12: =IF(H12="","",IF(H12>=I12,"On target",IF(H12>=0.7*I12,"Underpriced","Money loser")))
G13: =IF(C13="","",C13-IF(F13="",0,F13)) | H13: =IF(OR(C13="",E13="",E13=0),"",G13/E13) | I13: =IF(C13="","",'Rate Calculator'!$B$16) | J13: =IF(OR(H13="",I13=""),"",H13-I13) | K13: =IF(H13="","",IF(H13>=I13,"On target",IF(H13>=0.7*I13,"Underpriced","Money loser")))
G14: =IF(C14="","",C14-IF(F14="",0,F14)) | H14: =IF(OR(C14="",E14="",E14=0),"",G14/E14) | I14: =IF(C14="","",'Rate Calculator'!$B$16) | J14: =IF(OR(H14="",I14=""),"",H14-I14) | K14: =IF(H14="","",IF(H14>=I14,"On target",IF(H14>=0.7*I14,"Underpriced","Money loser")))
G15: =IF(C15="","",C15-IF(F15="",0,F15)) | H15: =IF(OR(C15="",E15="",E15=0),"",G15/E15) | I15: =IF(C15="","",'Rate Calculator'!$B$16) | J15: =IF(OR(H15="",I15=""),"",H15-I15) | K15: =IF(H15="","",IF(H15>=I15,"On target",IF(H15>=0.7*I15,"Underpriced","Money loser")))
G16: =IF(C16="","",C16-IF(F16="",0,F16)) | H16: =IF(OR(C16="",E16="",E16=0),"",G16/E16) | I16: =IF(C16="","",'Rate Calculator'!$B$16) | J16: =IF(OR(H16="",I16=""),"",H16-I16) | K16: =IF(H16="","",IF(H16>=I16,"On target",IF(H16>=0.7*I16,"Underpriced","Money loser")))
G17: =IF(C17="","",C17-IF(F17="",0,F17)) | H17: =IF(OR(C17="",E17="",E17=0),"",G17/E17) | I17: =IF(C17="","",'Rate Calculator'!$B$16) | J17: =IF(OR(H17="",I17=""),"",H17-I17) | K17: =IF(H17="","",IF(H17>=I17,"On target",IF(H17>=0.7*I17,"Underpriced","Money loser")))
G18: =IF(C18="","",C18-IF(F18="",0,F18)) | H18: =IF(OR(C18="",E18="",E18=0),"",G18/E18) | I18: =IF(C18="","",'Rate Calculator'!$B$16) | J18: =IF(OR(H18="",I18=""),"",H18-I18) | K18: =IF(H18="","",IF(H18>=I18,"On target",IF(H18>=0.7*I18,"Underpriced","Money loser")))
G19: =IF(C19="","",C19-IF(F19="",0,F19)) | H19: =IF(OR(C19="",E19="",E19=0),"",G19/E19) | I19: =IF(C19="","",'Rate Calculator'!$B$16) | J19: =IF(OR(H19="",I19=""),"",H19-I19) | K19: =IF(H19="","",IF(H19>=I19,"On target",IF(H19>=0.7*I19,"Underpriced","Money loser")))
G20: =IF(C20="","",C20-IF(F20="",0,F20)) | H20: =IF(OR(C20="",E20="",E20=0),"",G20/E20) | I20: =IF(C20="","",'Rate Calculator'!$B$16) | J20: =IF(OR(H20="",I20=""),"",H20-I20) | K20: =IF(H20="","",IF(H20>=I20,"On target",IF(H20>=0.7*I20,"Underpriced","Money loser")))
G21: =IF(C21="","",C21-IF(F21="",0,F21)) | H21: =IF(OR(C21="",E21="",E21=0),"",G21/E21) | I21: =IF(C21="","",'Rate Calculator'!$B$16) | J21: =IF(OR(H21="",I21=""),"",H21-I21) | K21: =IF(H21="","",IF(H21>=I21,"On target",IF(H21>=0.7*I21,"Underpriced","Money loser")))
... G204: =IF(C204="","",C204-IF(F204="",0,F204)) | H204: =IF(OR(C204="",E204="",E204=0),"",G204/E204) | I204: =IF(C204="","",'Rate Calculator'!$B$16) | J204: =IF(OR(H204="",I204=""),"",H204-I204) | K204: =IF(H204="","",IF(H204>=I204,"On target",IF(H204>=0.7*I204,"Underpriced","Money loser")))

Sheet Time Log
A1: Time log
A2: Log hours per project. Weekly total shows your real billable load.
A4: Date | B4: Project | C4: Hours | D4: Billable? (Y/N) | E4: Notes | F4: Week starts | H4: Total hours | I4: =SUM(C5:C504)
A5: 46272 | B5: Logo pack | C5: 5 | D5: Y | E5: sketches | F5: =IF(A5="","",A5-WEEKDAY(A5,2)+1) | H5: Billable hours | I5: =SUMIFS(C5:C504,D5:D504,"Y")
A6: 46273 | B6: Website | C6: 6 | D6: Y | F6: =IF(A6="","",A6-WEEKDAY(A6,2)+1) | H6: Billable share | I6: =IF(I4=0,0,I5/I4)
A7: 46274 | B7: Admin | C7: 2 | D7: N | E7: invoicing | F7: =IF(A7="","",A7-WEEKDAY(A7,2)+1)
A8: 46279 | B8: Website | C8: 4 | D8: Y | F8: =IF(A8="","",A8-WEEKDAY(A8,2)+1)
F9: =IF(A9="","",A9-WEEKDAY(A9,2)+1)
F10: =IF(A10="","",A10-WEEKDAY(A10,2)+1)
F11: =IF(A11="","",A11-WEEKDAY(A11,2)+1)
F12: =IF(A12="","",A12-WEEKDAY(A12,2)+1)
F13: =IF(A13="","",A13-WEEKDAY(A13,2)+1)
F14: =IF(A14="","",A14-WEEKDAY(A14,2)+1)
F15: =IF(A15="","",A15-WEEKDAY(A15,2)+1)
F16: =IF(A16="","",A16-WEEKDAY(A16,2)+1)
F17: =IF(A17="","",A17-WEEKDAY(A17,2)+1)
F18: =IF(A18="","",A18-WEEKDAY(A18,2)+1)
F19: =IF(A19="","",A19-WEEKDAY(A19,2)+1)
F20: =IF(A20="","",A20-WEEKDAY(A20,2)+1)
... F504: =IF(A504="","",A504-WEEKDAY(A504,2)+1)
